{"version":1,"functions":{"/api/admin/security-stats":{},"/api/auth/demo-login":{},"/api/auth/login":{},"/api/auth/register":{},"/api/auth/refresh":{},"/api/analytics/stats":{},"/api/cron/cleanup":{},"/api/biometric/face":{},"/api/cron/health-check":{},"/api/face-verification-test":{},"/api/health":{},"/api/payments/analytics":{},"/api/payments/methods/[id]":{},"/api/payments/stripe/checkout":{},"/api/payments/stripe/payment-intent":{},"/api/payments/stripe/setup-intent":{},"/api/payments/stripe/refund":{},"/api/payments/methods":{},"/api/payments/stripe/webhook":{},"/api/transactions/[id]":{},"/api/transactions/[id]/receipt":{},"/api/transactions/bulk":{},"/api/transactions":{},"/api/version":{},"/api/transactions/[id]/refund":{},"/api/webauthn/authenticate-options":{},"/api/webauthn/authenticate-verify":{},"/api/webauthn/authenticate/options":{},"/api/webauthn/authenticate/complete":{},"/api/transactions/history":{},"/api/webauthn/authenticate/start":{},"/api/users/profile":{},"/api/webauthn/demo-register/complete":{},"/api/webauthn/credentials":{},"/api/webauthn/demo-register/start":{},"/api/webauthn/register-verify":{},"/api/webauthn/register-options":{},"/api/webauthn/login":{},"/api/webauthn/register/complete":{},"/api/webauthn/register/options":{},"/api/webauthn/register":{},"/api/webauthn/register/start":{}}}